Metadata-Version: 2.4
Name: mindkosh
Version: 1.0.2
Summary: Mindkosh Python SDK
Home-page: https://github.com/Mindkosh/mindkosh-python-sdk
Author: Mindkosh
Author-email: shikhar@mindkosh.com
License: Apache-2.0
Keywords: annotation,segmentation,pointcloud,computervision
Requires-Python: >=3.7
License-File: LICENSE
Requires-Dist: requests==2.31.0
Requires-Dist: typing-extensions==4.7.1
Requires-Dist: numpy==1.21.6
Requires-Dist: Pillow==9.2.0
Requires-Dist: kiwisolver==1.4.4
Requires-Dist: matplotlib==3.5.1
Requires-Dist: mplcursors==0.5.1
Requires-Dist: aiohttp==3.8.6
Requires-Dist: alive-progress==2.4.1
Requires-Dist: validators==0.20.0
Requires-Dist: python-dotenv==0.21.0
Dynamic: author
Dynamic: author-email
Dynamic: description
Dynamic: description-content-type
Dynamic: home-page
Dynamic: keywords
Dynamic: license
Dynamic: license-file
Dynamic: requires-dist
Dynamic: requires-python
Dynamic: summary
